Metadata-Version: 2.1
Name: zmx_hello
Version: 0.0.1
Summary: A hello world
Author: rehmet
